LICENSE
MANIFEST.in
README.md
pyproject.toml
setup.cfg
mychamp/__init__.py
mychamp/__main__.py
mychamp/meta.py
mychamp/meta.sh
mychamp.egg-info/PKG-INFO
mychamp.egg-info/SOURCES.txt
mychamp.egg-info/dependency_links.txt
mychamp.egg-info/entry_points.txt
mychamp.egg-info/top_level.txt
mychamp/data/__init__.py
mychamp/data/quote.txt
mychamp/machamp/__init__.py
mychamp/machamp/util.py
mychamp/machamp/dataset_readers/__init__.py
mychamp/machamp/dataset_readers/basic_tokenizer.py
mychamp/machamp/dataset_readers/lemma_edit.py
mychamp/machamp/dataset_readers/machamp_universal_reader.py
mychamp/machamp/dataset_readers/reader_utils.py
mychamp/machamp/dataset_readers/sequence_multilabel_field.py
mychamp/machamp/metrics/__init__.py
mychamp/machamp/metrics/multi_span_based_f1_measure.py
mychamp/machamp/metrics/perplexity.py
mychamp/machamp/models/__init__.py
mychamp/machamp/models/crf_decoder.py
mychamp/machamp/models/dependency_decoder.py
mychamp/machamp/models/machamp_model.py
mychamp/machamp/models/mlm_decoder.py
mychamp/machamp/models/multiseq_decoder.py
mychamp/machamp/models/sentence_decoder.py
mychamp/machamp/models/seq2seq_decoder.py
mychamp/machamp/models/tag_decoder.py
mychamp/machamp/modules/__init__.py
mychamp/machamp/modules/bucket_batch_sampler.py
mychamp/machamp/modules/pretrained_transformer_embedder.py
mychamp/machamp/modules/pretrained_transformer_mismatched_embedder.py
mychamp/machamp/modules/pretrained_transformer_mixmatched_indexer.py
mychamp/machamp/predictor/__init__.py
mychamp/machamp/predictor/predictor.py
mychamp/predict/__main__.py
mychamp/train/__main__.py
mychamp/train/arguments.py