Metadata-Version: 2.1
Name: mychamp
Version: 0.0.2
Summary: Stub files to use as the basis of a Python project that can be packaged and uploaded to PyPI
Home-page: https://github.com/striebel/mychamp
Author: Striebel
Author-email: jacob.striebel@example.com
License: MIT
Project-URL: Homepage, https://github.com/striebel/mychamp
License-File: LICENSE
